TopDownHockey_Scraper/TopDownHockey_EliteProspects_Scraper.py
TopDownHockey_Scraper/TopDownHockey_NHL_Scraper.py
TopDownHockey_Scraper/TopDownHockey_NHL_Scraper_OG.py
TopDownHockey_Scraper/TopDownHockey_NHL_Scraper_fixed.py
TopDownHockey_Scraper/__init__.py
TopDownHockey_Scraper/name_corrections.py
TopDownHockey_Scraper/portrait_links.csv
TopDownHockey_Scraper/scrape_nhl_api_events.py
TopDownHockey_Scraper/data/handedness.csv
topdownhockey_scraper-6.1.40.dist-info/licenses/LICENSE
topdownhockey_scraper-6.1.40.dist-info/METADATA
topdownhockey_scraper-6.1.40.dist-info/WHEEL
topdownhockey_scraper-6.1.40.dist-info/top_level.txt
topdownhockey_scraper-6.1.40.dist-info/RECORD
