Metadata-Version: 2.4
Name: TopDownHockey_Scraper
Version: 6.1.40
Summary: The TopDownHockey Scraper
Home-page: https://github.com/TopDownHockey/TopDownHockey_Scraper
Author: Patrick Bacon
Author-email: patrick.s.bacon@gmail.com
License: MIT
Project-URL: Bug Tracker, https://github.com/TopDownHockey/TopDownHockey_Scraper/issues
Classifier: Programming Language :: Python :: 3
Classifier: License :: OSI Approved :: MIT License
Classifier: Operating System :: OS Independent
Requires-Python: >=3.6
License-File: LICENSE
Requires-Dist: numpy
Requires-Dist: pandas
Requires-Dist: bs4
Requires-Dist: requests
Requires-Dist: xmltodict
Requires-Dist: lxml
Requires-Dist: natsort
Dynamic: author
Dynamic: author-email
Dynamic: classifier
Dynamic: description
Dynamic: description-content-type
Dynamic: home-page
Dynamic: license
Dynamic: license-file
Dynamic: project-url
Dynamic: requires-dist
Dynamic: requires-python
Dynamic: summary
